{
    "qtype": "CHOICE",
    "quest_stem": {
        "options": [
            {
                "bullet": "A",
                "text": "5是因数"
            },
            {
                "bullet": "B",
                "text": "7是因数"
            },
            {
                "bullet": "C",
                "text": "35是倍数"
            },
            {
                "bullet": "D",
                "text": "5是35的因数"
            }
        ],
        "text": "对于乘法算式5×7=35，下面的说法中，正确的是( ) "
    },
    "quest_ref": {
        "texts": [
            "D"
        ],
        "analyses": [
            "因数和倍数是相对的，是相互依存的，不能单独存在，只能说一个数是另一个数的倍数或另一个数是这个数的因数;据此判断即可."
        ]
    }
}