{
    "qtype": "CHOICE",
    "quest_stem": {
        "options": [
            {
                "bullet": "A",
                "text": "2"
            },
            {
                "bullet": "B",
                "text": "4"
            },
            {
                "bullet": "C",
                "text": "3"
            }
        ],
        "text": "妈妈早上8:00上班，中午11:00下班，她上午工作了( )小时. "
    },
    "quest_ref": {
        "texts": [
            "C"
        ],
        "analyses": [
            "本题主要是考查学生怎样计算简单的经过时间，我们可以直接用大时间减去小时间即可，11-8=3(个)小时."
        ]
    }
}