{
    "qtype": "CHOICE",
    "quest_stem": {
        "options": [
            {
                "bullet": "A",
                "text": "这组数据的平均数是11，众数是11，中位数是13"
            },
            {
                "bullet": "B",
                "text": "这组数据的平均数是12，众数是14，中位数是12"
            },
            {
                "bullet": "C",
                "text": "这组数据的平均数是12，众数是11，中位数是14"
            },
            {
                "bullet": "D",
                "text": "这组数据的平均数是12，众数是11，中位数是11.5"
            }
        ],
        "text": "某管乐小队同学的年龄分别是:11岁、12岁、11岁、14岁、14岁、11岁、12岁、11岁.那么下面说法正确的是( ) "
    },
    "quest_ref": {
        "texts": [
            "D"
        ],
        "analyses": [
            "在一组数据中，用这组数据的总和除以数据的个数就是这组数据的平均数;在这组数据中出现次数最多的数据叫作这组数据的众数;将这组数据按照从小到大的顺序进行排列，排在中间位置的数据叫作这组数据的中位数，若这组数据为偶数位，那么排在中间的两个数据的平均数即是这组数据的中位数."
        ]
    }
}