{
    "qtype": "CHOICE",
    "quest_stem": {
        "options": [
            {
                "bullet": "A",
                "text": "700"
            },
            {
                "bullet": "B",
                "text": "800"
            },
            {
                "bullet": "C",
                "text": "900"
            }
        ],
        "text": "298+597的和最接近( ). "
    },
    "quest_ref": {
        "texts": [
            "C"
        ],
        "analyses": [
            "根据算式特点理解加法的运算定律，能够正确对结果进行估计.在估算时，把数看成与它接近的整十整百数进行估算."
        ]
    }
}