{
    "qtype": "CHOICE",
    "quest_stem": {
        "options": [
            {
                "bullet": "A",
                "text": "700"
            },
            {
                "bullet": "B",
                "text": "300"
            },
            {
                "bullet": "C",
                "text": "200"
            }
        ],
        "text": "估算499-201的结果大约是( ). "
    },
    "quest_ref": {
        "texts": [
            "B"
        ],
        "analyses": [
            "根据题意计算出减法的结果，再找大约数.解: 499-201=298，298极其接近的整数是300，所以大约是300.故答案为:b"
        ]
    }
}