{
    "qtype": "CHOICE",
    "quest_stem": {
        "options": [
            {
                "bullet": "A",
                "text": "先向东北走，再向西北走"
            },
            {
                "bullet": "B",
                "text": "先向东南走，再向西南走"
            },
            {
                "bullet": "C",
                "text": "先向西南走，再向东南走"
            }
        ],
        "text": "贝贝从家去商场时先向西北走，再向东北走到商场。原路返回时应该 ( )才能按原路回家。"
    },
    "quest_ref": {
        "texts": [
            "C"
        ],
        "analyses": [
            "贝贝原路返回即可，西北和东南相对，东北和西南相对，所以先向西南走，再向东南走，所以应选C。"
        ]
    }
}