{
    "qtype": "CHOICE",
    "quest_stem": {
        "options": [
            {
                "bullet": "A",
                "text": "60"
            },
            {
                "bullet": "B",
                "text": "40"
            },
            {
                "bullet": "C",
                "text": "30"
            }
        ],
        "text": "一个正方体的木料，它的底面积是10平方厘米，把它横截成4段相同的长方体，表面积增加( )平方厘米。 "
    },
    "quest_ref": {
        "texts": [
            "A"
        ],
        "analyses": [
            "10×6=60(平方厘米)  横截成4段相同的长方体，相当于多了6个横截面，也就是6个10平方厘米。"
        ]
    }
}