{
    "qtype": "CHOICE",
    "quest_stem": {
        "options": [
            {
                "bullet": "A",
                "text": "比原来小"
            },
            {
                "bullet": "B",
                "text": "比原来大"
            },
            {
                "bullet": "C",
                "text": "一样大"
            },
            {
                "bullet": "D",
                "text": "无法比较"
            }
        ],
        "text": "把一个长方体切成两块，切割后的体积之和与原来的体积比较( ) "
    },
    "quest_ref": {
        "texts": [
            "C"
        ],
        "analyses": [
            "由题意可知:一个长方体切成两个大小相等的正方体后，分成的两个正方体所占据空间的大小和就等于原来长方体的体积，所以体积不变，据此解答即可."
        ]
    }
}