{
    "qtype": "CHOICE",
    "quest_stem": {
        "options": [
            {
                "bullet": "A",
                "text": "135×(1+25%)"
            },
            {
                "bullet": "B",
                "text": "135×(1-25%)"
            },
            {
                "bullet": "C",
                "text": "135÷25%"
            },
            {
                "bullet": "D",
                "text": "135÷(1-25%)"
            }
        ],
        "text": "某机关现有工作人员135人，比原来精简了25%，原有工作人员多少人?列式是( ) "
    },
    "quest_ref": {
        "texts": [
            "D"
        ],
        "analyses": [
            "把原有工作人员人数看作单位‘1‘，比原来精简了25%，所以现在是原来的1-25%=75%，已知现有工作人员135人，也就是135人是原来的75%，则原有工作人员135÷75%，解决问题."
        ]
    }
}